dashboard_pkg/__init__.py
dashboard_pkg/covid_data_handler.py
dashboard_pkg/covid_news_handling.py
dashboard_pkg/main.py
dashboard_pkg_mtrenchard-1.0.dist-info/LICENSE.txt.txt
dashboard_pkg_mtrenchard-1.0.dist-info/METADATA
dashboard_pkg_mtrenchard-1.0.dist-info/WHEEL
dashboard_pkg_mtrenchard-1.0.dist-info/top_level.txt
dashboard_pkg_mtrenchard-1.0.dist-info/RECORD
