Metadata-Version: 2.1
Name: dashboard-pkg-mtrenchard
Version: 1.0
Summary: A covid dashboard providing the latest Covid information. To be used for demonstration.
Home-page: https://github.com/m4ttT10/2021-Covid-Dashboard-CA
Author: Matt Trenchard
Author-email: mjt235@exeter.ac.uk
License: UNKNOWN
Platform: UNKNOWN
Classifier: Programming Language :: Python :: 3
Classifier: License :: OSI Approved :: MIT License
Classifier: Operating System :: OS Independent
Requires-Python: >=3.10
License-File: LICENSE.txt.txt
